pupilcloud
