Metadata-Version: 1.0
Name: pupilcloud
Version: 1.0.1
Summary: Pupil Cloud
Home-page: UNKNOWN
Author: Pupil Labs
Author-email: info@pupil-labs.com
License: UNKNOWN
Keywords: OpenAPI,Pupil Cloud
Platform: UNKNOWN
